django_bsdatetime/__init__.py
django_bsdatetime/fields.py
django_bsdatetime-1.0.1.dist-info/licenses/LICENSE
django_bsdatetime-1.0.1.dist-info/METADATA
django_bsdatetime-1.0.1.dist-info/WHEEL
django_bsdatetime-1.0.1.dist-info/top_level.txt
django_bsdatetime-1.0.1.dist-info/RECORD
