Metadata-Version: 2.4
Name: django-bsdatetime
Version: 1.0.1
Summary: Django model fields for Bikram Sambat (Nepali) dates (built on bsdatetime)
Home-page: https://github.com/Rajendra-Katuwal/django-bsdatetime
Author: Rajendra Katuwal
Author-email: Rajendra Katuwal <raj.katuwal2061@gmail.com>
License: MIT
Project-URL: Homepage, https://github.com/Rajendra-Katuwal/django-bsdatetime
Project-URL: Documentation, https://rajendra-katuwal.github.io/bsdatetime.docs/
Project-URL: Issues, https://github.com/Rajendra-Katuwal/django-bsdatetime/issues
Project-URL: Source, https://github.com/Rajendra-Katuwal/django-bsdatetime
Keywords: django,bikram sambat,nepali,calendar,date,datetime,fields
Classifier: Framework :: Django
Classifier: Framework :: Django :: 3.2
Classifier: Framework :: Django :: 4.0
Classifier: Framework :: Django :: 4.1
Classifier: Framework :: Django :: 4.2
Classifier: Framework :: Django :: 5.0
Classifier: Intended Audience :: Developers
Classifier: Topic :: Software Development :: Internationalization
Classifier: Programming Language :: Python :: 3
Classifier: Programming Language :: Python :: 3.9
Classifier: Programming Language :: Python :: 3.10
Classifier: Programming Language :: Python :: 3.11
Classifier: Programming Language :: Python :: 3.12
Classifier: License :: OSI Approved :: MIT License
Classifier: Operating System :: OS Independent
Classifier: Development Status :: 5 - Production/Stable
Classifier: Environment :: Web Environment
Classifier: Topic :: Internet :: WWW/HTTP
Classifier: Topic :: Software Development :: Libraries :: Python Modules
Requires-Python: >=3.9
License-File: LICENSE
Requires-Dist: Django>=3.2
Requires-Dist: bsdatetime>=1.0.1
Dynamic: author
Dynamic: home-page
Dynamic: license-file
Dynamic: requires-python
